numena/__init__.py
numena/dataset/__init__.py
numena/dataset/base.py
numena/enums.py
numena/features/__init__.py
numena/features/pandas.py
numena/features/profiling.py
numena/figure.py
numena/geometry.py
numena/image/__init__.py
numena/image/basics.py
numena/image/color.py
numena/image/contour.py
numena/image/drawing.py
numena/image/geometry.py
numena/image/morphology.py
numena/image/operator.py
numena/image/threshold.py
numena/image/types.py
numena/io/__init__.py
numena/io/colors.png
numena/io/drive.py
numena/io/image.py
numena/io/imagej.py
numena/io/json.py
numena/time.py
numena-0.1.2.dist-info/LICENSE
numena-0.1.2.dist-info/WHEEL
numena-0.1.2.dist-info/METADATA
numena-0.1.2.dist-info/RECORD
